{
   "AutoCAM审核" : {
      "AutoCAM_Checks_Result" : 1,
      "audit_free_result" : 0
   },
   "Profile数据" : {
      "GongBeltLength" : 1043620.70633,
      "MinSlotWide" : 0,
      "ProfileLayer" : "gko",
      "Profile半孔" : 0,
      "Profile半孔直径" : 0,
      "Profile类型" : 1,
      "Profile面积" : 71452458818,
      "Profile异形比" : 0.996938856502,
      "panel_x" : 1,
      "panel_y" : 1,
      "板的款数" : 1,
      "板内槽长" : 0,
      "分板类型" : -1,
      "锣带轨迹" : 57327.1452702,
      "数组" : [
         {
            "e" : {
               "x" : 472884,
               "y" : -486983
            },
            "geotype" : 0,
            "s" : {
               "x" : 471008,
               "y" : -483997
            }
         },
         {
            "e" : {
               "x" : 475378,
               "y" : -489477
            },
            "geotype" : 0,
            "s" : {
               "x" : 472884,
               "y" : -486983
            }
         },
         {
            "e" : {
               "x" : 478364,
               "y" : -491353
            },
            "geotype" : 0,
            "s" : {
               "x" : 475378,
               "y" : -489477
            }
         },
         {
            "e" : {
               "x" : 481692,
               "y" : -492518
            },
            "geotype" : 0,
            "s" : {
               "x" : 478364,
               "y" : -491353
            }
         },
         {
            "e" : {
               "x" : 485197,
               "y" : -492913
            },
            "geotype" : 0,
            "s" : {
               "x" : 481692,
               "y" : -492518
            }
         },
         {
            "e" : {
               "x" : 721417,
               "y" : -492913
            },
            "geotype" : 0,
            "s" : {
               "x" : 485197,
               "y" : -492913
            }
         },
         {
            "e" : {
               "x" : 724921,
               "y" : -492518
            },
            "geotype" : 0,
            "s" : {
               "x" : 721417,
               "y" : -492913
            }
         },
         {
            "e" : {
               "x" : 728249,
               "y" : -491353
            },
            "geotype" : 0,
            "s" : {
               "x" : 724921,
               "y" : -492518
            }
         },
         {
            "e" : {
               "x" : 731235,
               "y" : -489477
            },
            "geotype" : 0,
            "s" : {
               "x" : 728249,
               "y" : -491353
            }
         },
         {
            "e" : {
               "x" : 733729,
               "y" : -486983
            },
            "geotype" : 0,
            "s" : {
               "x" : 731235,
               "y" : -489477
            }
         },
         {
            "e" : {
               "x" : 735605,
               "y" : -483997
            },
            "geotype" : 0,
            "s" : {
               "x" : 733729,
               "y" : -486983
            }
         },
         {
            "e" : {
               "x" : 736770,
               "y" : -480669
            },
            "geotype" : 0,
            "s" : {
               "x" : 735605,
               "y" : -483997
            }
         },
         {
            "e" : {
               "x" : 737165,
               "y" : -477165
            },
            "geotype" : 0,
            "s" : {
               "x" : 736770,
               "y" : -480669
            }
         },
         {
            "e" : {
               "x" : 737165,
               "y" : -240945
            },
            "geotype" : 0,
            "s" : {
               "x" : 737165,
               "y" : -477165
            }
         },
         {
            "e" : {
               "x" : 736770,
               "y" : -237440
            },
            "geotype" : 0,
            "s" : {
               "x" : 737165,
               "y" : -240945
            }
         },
         {
            "e" : {
               "x" : 735605,
               "y" : -234112
            },
            "geotype" : 0,
            "s" : {
               "x" : 736770,
               "y" : -237440
            }
         },
         {
            "e" : {
               "x" : 733729,
               "y" : -231126
            },
            "geotype" : 0,
            "s" : {
               "x" : 735605,
               "y" : -234112
            }
         },
         {
            "e" : {
               "x" : 731235,
               "y" : -228632
            },
            "geotype" : 0,
            "s" : {
               "x" : 733729,
               "y" : -231126
            }
         },
         {
            "e" : {
               "x" : 728249,
               "y" : -226756
            },
            "geotype" : 0,
            "s" : {
               "x" : 731235,
               "y" : -228632
            }
         },
         {
            "e" : {
               "x" : 724921,
               "y" : -225591
            },
            "geotype" : 0,
            "s" : {
               "x" : 728249,
               "y" : -226756
            }
         },
         {
            "e" : {
               "x" : 721417,
               "y" : -225197
            },
            "geotype" : 0,
            "s" : {
               "x" : 724921,
               "y" : -225591
            }
         },
         {
            "e" : {
               "x" : 485197,
               "y" : -225197
            },
            "geotype" : 0,
            "s" : {
               "x" : 721417,
               "y" : -225197
            }
         },
         {
            "e" : {
               "x" : 481692,
               "y" : -225591
            },
            "geotype" : 0,
            "s" : {
               "x" : 485197,
               "y" : -225197
            }
         },
         {
            "e" : {
               "x" : 478364,
               "y" : -226756
            },
            "geotype" : 0,
            "s" : {
               "x" : 481692,
               "y" : -225591
            }
         },
         {
            "e" : {
               "x" : 475378,
               "y" : -228632
            },
            "geotype" : 0,
            "s" : {
               "x" : 478364,
               "y" : -226756
            }
         },
         {
            "e" : {
               "x" : 472884,
               "y" : -231126
            },
            "geotype" : 0,
            "s" : {
               "x" : 475378,
               "y" : -228632
            }
         },
         {
            "e" : {
               "x" : 471008,
               "y" : -234112
            },
            "geotype" : 0,
            "s" : {
               "x" : 472884,
               "y" : -231126
            }
         },
         {
            "e" : {
               "x" : 469843,
               "y" : -237440
            },
            "geotype" : 0,
            "s" : {
               "x" : 471008,
               "y" : -234112
            }
         },
         {
            "e" : {
               "x" : 469449,
               "y" : -240945
            },
            "geotype" : 0,
            "s" : {
               "x" : 469843,
               "y" : -237440
            }
         },
         {
            "e" : {
               "x" : 469449,
               "y" : -477165
            },
            "geotype" : 0,
            "s" : {
               "x" : 469449,
               "y" : -240945
            }
         },
         {
            "e" : {
               "x" : 469843,
               "y" : -480669
            },
            "geotype" : 0,
            "s" : {
               "x" : 469449,
               "y" : -477165
            }
         },
         {
            "e" : {
               "x" : 471008,
               "y" : -483997
            },
            "geotype" : 0,
            "s" : {
               "x" : 469843,
               "y" : -480669
            }
         }
      ]
   },
   "audit_disk_hole_info" : {
      "disk_hole_ratio" : 0,
      "is_execution" : 1,
      "reliability" : -1
   },
   "audit_half_hole" : {
      "half_holes_is_execution" : 1,
      "half_holes_min_dia_mm" : 0
   },
   "audit_hdi_info" : {
      "is_execution" : 1,
      "is_hdi" : 0,
      "min_blind_dia_mm" : -1,
      "min_buried_dia_mm" : -1,
      "reliability" : 1
   },
   "audit_order_parameters" : {
      "parameters" : "{\"viaFilled\":\"过孔塞油\",\"orderType\":\"样板\",\"stencilType\":1,\"sestencilCountX\":0,\"sestencilCountY\":0,\"customerOrderId\":\"11415079\",\"isBacktosingle\":\"order\",\"orderCnt\":5,\"customId\":\"10385534\",\"customCode\":\"12421607A\",\"stencilNumber\":1,\"outerCopperThickness\":1.0,\"plateletCount\":0,\"spaceSizeX\":0.0,\"isMadeSmt\":0,\"BoardType\":1,\"spaceSizeY\":0.0,\"technicsBordersX\":0.0,\"technicsBordersY\":0.0,\"boardThickness\":1.6,\"InnerCopperThickness\":0.5}"
   },
   "audit_via_info" : {
      "is_execution" : 1,
      "limit_max_drl_dia_mm" : 0.32562,
      "limit_min_drl_dia_mm" : 0,
      "limit_of_quantity" : 100,
      "reliability" : 1,
      "via_array" : [
         {
            "center_pos" : {
               "x_mm" : 120.220478,
               "y_mm" : -83.959454
            },
            "drl_dia_mm" : 0.30022,
            "layer_name" : "tl",
            "pad_dia_mm" : 0.600448
         }
      ]
   },
   "set常规信息" : {
      "拼板审核结果" : -1,
      "拼板审核结果描述" : "暂未支持的拼板方式"
   },
   "八角焊盘" : {
      "八角焊盘" : 0
   },
   "备注信息" : {
      "总备注" : ""
   },
   "补充信息" : {
      "additional_msg" : "",
      "maybe_iv_msg" : ""
   },
   "测试点" : {
      "点数" : 100
   },
   "层数据" : [
      {
         "层名" : "dd1",
         "负片信息" : {
            "概率" : 1,
            "全为独立Pad" : false,
            "是否负片" : 0
         },
         "镜像信息" : {
            "镜像x轴坐标" : 0,
            "镜像y轴坐标" : 0,
            "镜像类型" : 0
         },
         "排序索引" : 13,
         "偏移" : {
            "x" : 0,
            "y" : 0
         },
         "文件格式" : {
            "D码公英制" : 2,
            "格式类型" : 1,
            "后省零" : false,
            "前省零" : true,
            "位数二" : 5,
            "位数一" : 4,
            "坐标公英制" : 2
         },
         "文件名" : "lora-PTH-drl_map.gbr",
         "行属性" : {
            "层类型" : "DRILLMARK",
            "极性" : true,
            "上下文" : "MISC"
         }
      },
      {
         "层名" : "dd",
         "负片信息" : {
            "概率" : 1,
            "全为独立Pad" : false,
            "是否负片" : 0
         },
         "镜像信息" : {
            "镜像x轴坐标" : 0,
            "镜像y轴坐标" : 0,
            "镜像类型" : 0
         },
         "排序索引" : 12,
         "偏移" : {
            "x" : 0,
            "y" : 0
         },
         "文件格式" : {
            "D码公英制" : 2,
            "格式类型" : 1,
            "后省零" : false,
            "前省零" : true,
            "位数二" : 5,
            "位数一" : 4,
            "坐标公英制" : 2
         },
         "文件名" : "lora-NPTH-drl_map.gbr",
         "行属性" : {
            "层类型" : "DRILLMARK",
            "极性" : true,
            "上下文" : "MISC"
         }
      },
      {
         "层名" : "l3",
         "负片信息" : {
            "概率" : 0.546505955363,
            "全为独立Pad" : false,
            "是否负片" : 0
         },
         "镜像信息" : {
            "镜像x轴坐标" : 0,
            "镜像y轴坐标" : 0,
            "镜像类型" : 0
         },
         "排序索引" : 5,
         "偏移" : {
            "x" : 0,
            "y" : 0
         },
         "文件格式" : {
            "D码公英制" : 2,
            "格式类型" : 1,
            "后省零" : false,
            "前省零" : true,
            "位数二" : 6,
            "位数一" : 4,
            "坐标公英制" : 2
         },
         "文件名" : "lora-In2_Cu.g2",
         "行属性" : {
            "层类型" : "SIGNAL",
            "极性" : true,
            "上下文" : "BOARD"
         }
      },
      {
         "层名" : "l2",
         "负片信息" : {
            "概率" : 0.609391559578,
            "全为独立Pad" : false,
            "是否负片" : 0
         },
         "镜像信息" : {
            "镜像x轴坐标" : 0,
            "镜像y轴坐标" : 0,
            "镜像类型" : 0
         },
         "排序索引" : 4,
         "偏移" : {
            "x" : 0,
            "y" : 0
         },
         "文件格式" : {
            "D码公英制" : 2,
            "格式类型" : 1,
            "后省零" : false,
            "前省零" : true,
            "位数二" : 6,
            "位数一" : 4,
            "坐标公英制" : 2
         },
         "文件名" : "lora-In1_Cu.g1",
         "行属性" : {
            "层类型" : "SIGNAL",
            "极性" : true,
            "上下文" : "BOARD"
         }
      },
      {
         "层名" : "to",
         "负片信息" : {
            "概率" : 1,
            "全为独立Pad" : false,
            "是否负片" : 0
         },
         "镜像信息" : {
            "镜像x轴坐标" : 0,
            "镜像y轴坐标" : 0,
            "镜像类型" : 0
         },
         "排序索引" : 0,
         "偏移" : {
            "x" : 0,
            "y" : 0
         },
         "文件格式" : {
            "D码公英制" : 2,
            "格式类型" : 1,
            "后省零" : false,
            "前省零" : true,
            "位数二" : 6,
            "位数一" : 4,
            "坐标公英制" : 2
         },
         "文件名" : "lora-F_Silkscreen.gto",
         "行属性" : {
            "层类型" : "SILK_SCREEN",
            "极性" : true,
            "上下文" : "BOARD"
         }
      },
      {
         "层名" : "tp",
         "负片信息" : {
            "概率" : 1,
            "全为独立Pad" : false,
            "是否负片" : 0
         },
         "镜像信息" : {
            "镜像x轴坐标" : 0,
            "镜像y轴坐标" : 0,
            "镜像类型" : 0
         },
         "排序索引" : 1,
         "偏移" : {
            "x" : 0,
            "y" : 0
         },
         "文件格式" : {
            "D码公英制" : 2,
            "格式类型" : 1,
            "后省零" : false,
            "前省零" : true,
            "位数二" : 6,
            "位数一" : 4,
            "坐标公英制" : 2
         },
         "文件名" : "lora-F_Paste.gtp",
         "行属性" : {
            "层类型" : "SOLDER_PASTE",
            "极性" : true,
            "上下文" : "BOARD"
         }
      },
      {
         "层名" : "ts",
         "负片信息" : {
            "概率" : 1,
            "全为独立Pad" : false,
            "是否负片" : 0
         },
         "镜像信息" : {
            "镜像x轴坐标" : 0,
            "镜像y轴坐标" : 0,
            "镜像类型" : 0
         },
         "排序索引" : 2,
         "偏移" : {
            "x" : 0,
            "y" : 0
         },
         "文件格式" : {
            "D码公英制" : 2,
            "格式类型" : 1,
            "后省零" : false,
            "前省零" : true,
            "位数二" : 6,
            "位数一" : 4,
            "坐标公英制" : 2
         },
         "文件名" : "lora-F_Mask.gts",
         "行属性" : {
            "层类型" : "SOLDER_MASK",
            "极性" : true,
            "上下文" : "BOARD"
         }
      },
      {
         "层名" : "tl",
         "负片信息" : {
            "概率" : 1,
            "全为独立Pad" : false,
            "是否负片" : 0
         },
         "镜像信息" : {
            "镜像x轴坐标" : 0,
            "镜像y轴坐标" : 0,
            "镜像类型" : 0
         },
         "排序索引" : 3,
         "偏移" : {
            "x" : 0,
            "y" : 0
         },
         "文件格式" : {
            "D码公英制" : 2,
            "格式类型" : 1,
            "后省零" : false,
            "前省零" : true,
            "位数二" : 6,
            "位数一" : 4,
            "坐标公英制" : 2
         },
         "文件名" : "lora-F_Cu.gtl",
         "行属性" : {
            "层类型" : "SIGNAL",
            "极性" : true,
            "上下文" : "BOARD"
         }
      },
      {
         "层名" : "gko",
         "负片信息" : {
            "概率" : 1,
            "全为独立Pad" : false,
            "是否负片" : 0
         },
         "镜像信息" : {
            "镜像x轴坐标" : 0,
            "镜像y轴坐标" : 0,
            "镜像类型" : 0
         },
         "排序索引" : 11,
         "偏移" : {
            "x" : 0,
            "y" : 0
         },
         "文件格式" : {
            "D码公英制" : 2,
            "格式类型" : 1,
            "后省零" : false,
            "前省零" : true,
            "位数二" : 6,
            "位数一" : 4,
            "坐标公英制" : 2
         },
         "文件名" : "lora-Edge_Cuts.gm1",
         "行属性" : {
            "层类型" : "ROUT",
            "极性" : true,
            "上下文" : "BOARD"
         }
      },
      {
         "层名" : "bo",
         "负片信息" : {
            "概率" : 1,
            "全为独立Pad" : false,
            "是否负片" : 0
         },
         "镜像信息" : {
            "镜像x轴坐标" : 0,
            "镜像y轴坐标" : 0,
            "镜像类型" : 0
         },
         "排序索引" : 9,
         "偏移" : {
            "x" : 0,
            "y" : 0
         },
         "文件格式" : {
            "D码公英制" : 2,
            "格式类型" : 1,
            "后省零" : false,
            "前省零" : true,
            "位数二" : 6,
            "位数一" : 4,
            "坐标公英制" : 2
         },
         "文件名" : "lora-B_Silkscreen.gbo",
         "行属性" : {
            "层类型" : "SILK_SCREEN",
            "极性" : true,
            "上下文" : "BOARD"
         }
      },
      {
         "层名" : "bp",
         "负片信息" : {
            "概率" : 1,
            "全为独立Pad" : false,
            "是否负片" : 0
         },
         "镜像信息" : {
            "镜像x轴坐标" : 0,
            "镜像y轴坐标" : 0,
            "镜像类型" : 0
         },
         "排序索引" : 8,
         "偏移" : {
            "x" : 0,
            "y" : 0
         },
         "文件格式" : {
            "D码公英制" : 2,
            "格式类型" : 1,
            "后省零" : false,
            "前省零" : true,
            "位数二" : 6,
            "位数一" : 4,
            "坐标公英制" : 2
         },
         "文件名" : "lora-B_Paste.gbp",
         "行属性" : {
            "层类型" : "SOLDER_PASTE",
            "极性" : true,
            "上下文" : "BOARD"
         }
      },
      {
         "层名" : "bs",
         "负片信息" : {
            "概率" : 1,
            "全为独立Pad" : false,
            "是否负片" : 0
         },
         "镜像信息" : {
            "镜像x轴坐标" : 0,
            "镜像y轴坐标" : 0,
            "镜像类型" : 0
         },
         "排序索引" : 7,
         "偏移" : {
            "x" : 0,
            "y" : 0
         },
         "文件格式" : {
            "D码公英制" : 2,
            "格式类型" : 1,
            "后省零" : false,
            "前省零" : true,
            "位数二" : 6,
            "位数一" : 4,
            "坐标公英制" : 2
         },
         "文件名" : "lora-B_Mask.gbs",
         "行属性" : {
            "层类型" : "SOLDER_MASK",
            "极性" : true,
            "上下文" : "BOARD"
         }
      },
      {
         "层名" : "bl",
         "负片信息" : {
            "概率" : 1,
            "全为独立Pad" : false,
            "是否负片" : 0
         },
         "镜像信息" : {
            "镜像x轴坐标" : 0,
            "镜像y轴坐标" : 0,
            "镜像类型" : 0
         },
         "排序索引" : 6,
         "偏移" : {
            "x" : 0,
            "y" : 0
         },
         "文件格式" : {
            "D码公英制" : 2,
            "格式类型" : 1,
            "后省零" : false,
            "前省零" : true,
            "位数二" : 6,
            "位数一" : 4,
            "坐标公英制" : 2
         },
         "文件名" : "lora-B_Cu.gbl",
         "行属性" : {
            "层类型" : "SIGNAL",
            "极性" : true,
            "上下文" : "BOARD"
         }
      },
      {
         "层名" : "drl",
         "负片信息" : {
            "概率" : 1,
            "全为独立Pad" : false,
            "是否负片" : 0
         },
         "镜像信息" : {
            "镜像x轴坐标" : 0,
            "镜像y轴坐标" : 0,
            "镜像类型" : 0
         },
         "排序索引" : 10,
         "偏移" : {
            "x" : 0,
            "y" : 0
         },
         "文件格式" : {
            "D码公英制" : 2,
            "格式类型" : 2,
            "后省零" : true,
            "前省零" : false,
            "位数二" : 0,
            "位数一" : 0,
            "坐标公英制" : 2
         },
         "文件名" : "lora-PTH.drl",
         "行属性" : {
            "层类型" : "DRILL",
            "极性" : true,
            "上下文" : "BOARD"
         }
      }
   ],
   "常规信息" : {
      "EDA类型" : "KICAD",
      "EasyEDA分数" : -300,
      "actex_lib_version" : "ACTEXLIB_V1.1.8",
      "猜测尺寸" : {
         "边沿间距(mm)" : 0.5,
         "长度" : 267714,
         "宽度" : 267714
      },
      "彩色文字" : 0,
      "层数" : 4,
      "单元尺寸" : {
         "长度" : 267716,
         "宽度" : 267716
      },
      "工艺边宽度" : 0,
      "套板尺寸" : {
         "长度" : 267716,
         "宽度" : 267716
      },
      "小板数量" : 1
   },
   "工作信息" : {
      "actex_lib_version" : "ACTEXLIB_V1.1.8",
      "checkreslut" : 0,
      "checksuccess" : true,
      "jobname" : "GBR_11415079_1"
   },
   "检测过孔" : {
      "arr" : [
         {
            "dia" : 2362,
            "id" : 322,
            "ly_name" : "tl",
            "pos" : {
               "x" : 473307,
               "y" : -330551
            }
         }
      ],
      "bga_info" : {
         "min_pad_dia_mm" : 0
      },
      "is_contain_qfn" : 0,
      "max_filter" : 3937,
      "min_dia" : 2362,
      "是否含无焊盘孔" : 0,
      "最大BGA含孔率" : -1,
      "最小BGA焊盘直径" : 0
   },
   "金手指" : {
      "金手指结果" : 0,
      "金手指区域是否无铜" : -1
   },
   "特殊板识别" : {
      "洞洞板" : 0,
      "键盘板" : -1,
      "喷锡洞洞板" : 0,
      "线圈板" : 0
   },
   "贴片信息" : null,
   "铜面积" : {
      "bl" : {
         "百分比" : 0.809463079096,
         "金百分比" : 0.0336662488558,
         "金孔壁面积" : 0.0997201851961,
         "金孔面积" : 0.0498600925981,
         "金面积" : 0.240553625993,
         "铜孔壁面积" : 0.746603237647,
         "铜孔面积" : 0.0830786159897,
         "铜面积" : 6.01873753788
      },
      "l2" : {
         "百分比" : 0.870459313574,
         "可靠度" : -1,
         "铜面积" : 6.21964582559
      },
      "l3" : {
         "百分比" : 0.780644082882,
         "可靠度" : -1,
         "铜面积" : 5.57789391836
      },
      "tl" : {
         "百分比" : 0.807837344827,
         "金百分比" : 0.055210178316,
         "金孔壁面积" : 0.0997201851961,
         "金孔面积" : 0.0498600925981,
         "金面积" : 0.394490299246,
         "铜孔壁面积" : 0.746603237647,
         "铜孔面积" : 0.0830786159897,
         "铜面积" : 6.00664944131
      }
   },
   "图片快照" : {
      "path" : "D:/work/B80C783FC55E40729DD1E741C7E48CD7/GBR_11415079_1/GBR_11415079_1_snapshot.png",
      "path_bottom" : "D:/work/B80C783FC55E40729DD1E741C7E48CD7/GBR_11415079_1/GBR_11415079_1_bottom.png",
      "path_top" : "D:/work/B80C783FC55E40729DD1E741C7E48CD7/GBR_11415079_1/GBR_11415079_1_top.png"
   },
   "重要文本" : {
      "qrcode_square_edge_mm" : 0,
      "检测结果" : 0
   },
   "钻孔信息" : {
      "drl" : {
         "槽孔数" : 0,
         "孔数" : 265,
         "无效槽数" : 0,
         "最小孔径" : 1180
      },
      "检测钻孔" : {
         "max_drl_dia_filter_mm" : 0.5,
         "plate_hole_ratio" : 0,
         "small_hole_density" : {
            "is_compliance" : 1
         },
         "扩孔扩槽孔数" : 0,
         "扩孔阔槽孔密度" : 0,
         "埋孔总数" : 0,
         "盲孔总数" : 0,
         "塞孔与非塞孔的最小距离" : 0,
         "双面铜基板有铜孔是否合规" : 1,
         "重复孔数" : 0,
         "钻槽长度" : 0,
         "钻孔密度" : 57309,
         "最大金属化孔的孔径" : 12598,
         "最小双面开窗孔径" : 0
      }
   },
   "最大露铜面积" : {
      "最大露铜面积" : 0
   },
   "最小线距" : {
      "arr" : [
         {
            "p1" : {
               "x" : 480169,
               "y" : -277741
            },
            "p2" : {
               "x" : 479577,
               "y" : -277149
            },
            "spacing" : 837,
            "层名" : "bl"
         },
         {
            "p1" : {
               "x" : 487780,
               "y" : -275614
            },
            "p2" : {
               "x" : 488480,
               "y" : -276314
            },
            "spacing" : 989,
            "层名" : "bl"
         },
         {
            "p1" : {
               "x" : 502810,
               "y" : -265684
            },
            "p2" : {
               "x" : 501795,
               "y" : -264669
            },
            "spacing" : 1435,
            "层名" : "bl"
         },
         {
            "p1" : {
               "x" : 473583,
               "y" : -325315
            },
            "p2" : {
               "x" : 475039,
               "y" : -325315
            },
            "spacing" : 1456,
            "层名" : "bl"
         },
         {
            "p1" : {
               "x" : 478716,
               "y" : -325378
            },
            "p2" : {
               "x" : 477603,
               "y" : -326491
            },
            "spacing" : 1574,
            "层名" : "tl"
         }
      ],
      "is_action" : 1,
      "is_action_open_space" : 1,
      "max" : 2000,
      "max_open_space" : 549
   },
   "最小线宽" : {
      "arr" : [
         {
            "pos" : [
               {
                  "x" : 617441,
                  "y" : -303252
               }
            ],
            "w" : 1182,
            "层名" : "tl"
         },
         {
            "pos" : [
               {
                  "x" : 689773,
                  "y" : -290403
               }
            ],
            "w" : 1182,
            "层名" : "bl"
         },
         {
            "pos" : [
               {
                  "x" : 609882,
                  "y" : -464665
               }
            ],
            "w" : 1968,
            "层名" : "tl"
         }
      ],
      "is_action" : 1,
      "max" : 2000
   }
}
